[
  {
    "id": 1,
    "name": "tail",
    "synopsis": "tail [OPTION]... [FILE]...",
    "tag": "test",
    "details": "Print the last 10 lines of each FILE to standard output. With more than one FILE, precede each with a header giving the file name",
    "options": [
      "Test option one",
      "Test option two"
    ],
    "description": "Description goes here"
  },
  {
    "id": 2,
    "name": "grep",
    "synopsis": "tail [OPTION]... [FILE]...",
    "tag": "test",
    "details": "Print the last 10 lines of each FILE to standard output. With more than one FILE, precede each with a header giving the file name",
    "options": [
      "Test option one",
      "Test option two"
    ],
    "description": "Description goes here"
  },
  {
    "id": 3,
    "name": "less",
    "synopsis": "tail [OPTION]... [FILE]...",
    "tag": "test",
    "details": "Print the last 10 lines of each FILE to standard output. With more than one FILE, precede each with a header giving the file name",
    "options": [
      "Test option one",
      "Test option two"
    ],
    "description": "Description goes here"
  },
  {
    "id": 11,
    "name": "tail",
    "synopsis": "tail [OPTION]... [FILE]...",
    "tag": "test",
    "details": "Print the last 10 lines of each FILE to standard output. With more than one FILE, precede each with a header giving the file name",
    "options": [
      "Test option one",
      "Test option two"
    ],
    "description": "Description goes here"
  },
  {
    "id": 22,
    "name": "grep",
    "synopsis": "tail [OPTION]... [FILE]...",
    "tag": "test",
    "details": "Print the last 10 lines of each FILE to standard output. With more than one FILE, precede each with a header giving the file name",
    "options": [
      "Test option one",
      "Test option two"
    ],
    "description": "Description goes here"
  },
  {
    "id": 33,
    "name": "less",
    "synopsis": "tail [OPTION]... [FILE]...",
    "tag": "test",
    "details": "Print the last 10 lines of each FILE to standard output. With more than one FILE, precede each with a header giving the file name",
    "options": [
      "Test option one",
      "Test option two"
    ],
    "description": "Description goes here"
  },
  {
    "id": 111,
    "name": "tail",
    "synopsis": "tail [OPTION]... [FILE]...",
    "tag": "test",
    "details": "Print the last 10 lines of each FILE to standard output. With more than one FILE, precede each with a header giving the file name",
    "options": [
      "Test option one",
      "Test option two"
    ],
    "description": "Description goes here"
  },
  {
    "id": 222,
    "name": "grep",
    "synopsis": "tail [OPTION]... [FILE]...",
    "tag": "test",
    "details": "Print the last 10 lines of each FILE to standard output. With more than one FILE, precede each with a header giving the file name",
    "options": [
      "Test option one",
      "Test option two"
    ],
    "description": "Description goes here"
  },
  {
    "id": 333,
    "name": "less",
    "synopsis": "tail [OPTION]... [FILE]...",
    "tag": "test",
    "details": "Print the last 10 lines of each FILE to standard output. With more than one FILE, precede each with a header giving the file name",
    "options": [
      "Test option one",
      "Test option two"
    ],
    "description": "Description goes here"
  },
  {
    "id": 1111,
    "name": "tail",
    "synopsis": "tail [OPTION]... [FILE]...",
    "tag": "test",
    "details": "Print the last 10 lines of each FILE to standard output. With more than one FILE, precede each with a header giving the file name",
    "options": [
      "Test option one",
      "Test option two"
    ],
    "description": "Description goes here"
  },
  {
    "id": 2222,
    "name": "grep",
    "synopsis": "tail [OPTION]... [FILE]...",
    "tag": "test",
    "details": "Print the last 10 lines of each FILE to standard output. With more than one FILE, precede each with a header giving the file name",
    "options": [
      "Test option one",
      "Test option two"
    ],
    "description": "Description goes here"
  },
  {
    "id": 3333,
    "name": "less",
    "synopsis": "tail [OPTION]... [FILE]...",
    "tag": "test",
    "details": "Print the last 10 lines of each FILE to standard output. With more than one FILE, precede each with a header giving the file name",
    "options": [
      "Test option one",
      "Test option two"
    ],
    "description": "Description goes here"
  },
  {
    "id": 11111,
    "name": "tail",
    "synopsis": "tail [OPTION]... [FILE]...",
    "tag": "test",
    "details": "Print the last 10 lines of each FILE to standard output. With more than one FILE, precede each with a header giving the file name",
    "options": [
      "Test option one",
      "Test option two"
    ],
    "description": "Description goes here"
  },
  {
    "id": 22222,
    "name": "grep",
    "synopsis": "tail [OPTION]... [FILE]...",
    "tag": "test",
    "details": "Print the last 10 lines of each FILE to standard output. With more than one FILE, precede each with a header giving the file name",
    "options": [
      "Test option one",
      "Test option two"
    ],
    "description": "Description goes here"
  },
  {
    "id": 33333,
    "name": "less",
    "synopsis": "tail [OPTION]... [FILE]...",
    "tag": "test",
    "details": "Print the last 10 lines of each FILE to standard output. With more than one FILE, precede each with a header giving the file name",
    "options": [
      "Test option one",
      "Test option two"
    ],
    "description": "Description goes here"
  }
]